{
  "f9855a4bc775449c566dabcd78c05fde759d0689.png": {
    "title": "Open Logo Small",
    "description": "Open Logo Small",
    "source": "https://theodi.org",
    "licence": "All rights reserved",
    "attribution": "The Open Data Institute",
    "tags": []
  },
  "d83ce940ff76810967a9ec101f4cb6fefd54a4d0.png": {
    "title": "Adapt eLearning",
    "description": "Adapt eLearning",
    "source": "unknown",
    "licence": "unknown",
    "attribution": "unknown",
    "tags": [
      {
        "title": "client logos",
        "_id": "5ee397aeb045644557c81aee"
      }
    ]
  },
  "ed8c41138dc38e9d42c4c464ef200a62b430716e.png": {
    "title": "ODI Learning Roundal Blue",
    "description": "Main ODI logo",
    "source": "http://theodi.org/",
    "licence": "All rights reserved",
    "attribution": "The Open Data Institute",
    "tags": [
      {
        "title": "ODI logo",
        "_id": "5ee397b8b045644557c81b50"
      },
      {
        "title": "intro logo",
        "_id": "5ee397b8b045644557c81b51"
      }
    ]
  },
  "50cd2a8785a924e204ab876d46a71c045cb0f0fc.png": {
    "title": "clipboard-update-round.png",
    "description": "clipbaord",
    "source": "theodi.org",
    "licence": "All rights reserved",
    "attribution": "ODI",
    "tags": []
  },
  "0e4cf59bb62a8520dec642e4bcbc169e90836ead.png": {
    "title": "Justice and fairness",
    "description": "Justice and fairness",
    "source": "https://www.theodi.org/",
    "licence": "CC-BY",
    "attribution": "The Open Data Institute",
    "tags": []
  },
  "30ecdf5a4cb05a98491d56e22e74143bcf6d7a74.png": {
    "title": "Ethics of care",
    "description": "Ethics of care",
    "source": "https://www.theodi.org/",
    "licence": "CC-BY",
    "attribution": "The Open Data Institute",
    "tags": []
  },
  "490e2795ecb4cb9aa547b000fe14e15de2c95f8c.png": {
    "title": "Virtue Ethics",
    "description": "Virtue Ethics",
    "source": "https://www.theodi.org/",
    "licence": "CC-BY",
    "attribution": "The Open Data Institute",
    "tags": []
  },
  "4a067fad57b41e099970dbcf4d50d1dfe05b0831.png": {
    "title": "Deontology",
    "description": "Deontology",
    "source": "https://www.theodi.org/",
    "licence": "CC-BY",
    "attribution": "The Open Data Institute",
    "tags": []
  },
  "ce234afcb6b1dd51bb01d3880a47ec416d417969.jpg": {
    "title": "trust",
    "description": "trust",
    "source": "https://elements.envato.com/trust-VQRDGSA",
    "licence": "Envato Element Licence",
    "attribution": "wanaktek",
    "tags": []
  },
  "cfd84842de4aeb90d325987f22279c3d7e8f36d6.jpg": {
    "title": "Business Evolution with AI",
    "description": "Business Evolution with AI",
    "source": "https://elements.envato.com/business-evolution-with-ai-interaction-with-modern-QX9AGST",
    "licence": "Envato Element Licence",
    "attribution": "AndersonPiza",
    "tags": []
  },
  "dc150d8858720bd2c77f7b074871dd34e938fa9a.jpg": {
    "title": "Work ethic",
    "description": "Work ethic",
    "source": "https://elements.envato.com/work-ethic-VYZJZJK",
    "licence": "Envato Element Licence",
    "attribution": "wanaktek",
    "tags": []
  },
  "ea5c5f3346fb1d7b245f38d85c08aaf7521db77d.jpg": {
    "title": "Questioning Your Approach to Challenges",
    "description": "Questioning Your Approach to Challenges",
    "source": "https://elements.envato.com/co-workers-are-discussing-presentation-of-business-7ULW3X3",
    "licence": "Envato Element Licence",
    "attribution": "Iakobchuk",
    "tags": []
  },
  "ec2c9a8ed91036d6c7dfe0e860356110b0e78f0a.png": {
    "title": "Rights based ethics",
    "description": "Rights based ethics",
    "source": "https://www.theodi.org/",
    "licence": "CC-BY",
    "attribution": "The Open Data Institute",
    "tags": []
  },
  "f411c2b78291072109c4c3a722e42c984411b0a9.png": {
    "title": "utilitarian",
    "description": "utilitarian",
    "source": "https://www.theodi.org/",
    "licence": "CC-BY",
    "attribution": "The Open Data Institute",
    "tags": []
  }
}